grandexchange/__init__.py
grandexchange/calculators.py
grandexchange/client.py
grandexchange/constants.py
grandexchange/endpoints.py
grandexchange/exceptions.py
grandexchange/items.py
grandexchange/transactions.py
grandexchange/static/godswords.yaml
grandexchange/static/sets.yaml
tests/__init__.py
tests/fixtures.py
tests/test_calculators.py
tests/test_items.py
tests/test_transactions.py
GrandExchangeToolbox-0.1.5.dist-info/METADATA
GrandExchangeToolbox-0.1.5.dist-info/WHEEL
GrandExchangeToolbox-0.1.5.dist-info/top_level.txt
GrandExchangeToolbox-0.1.5.dist-info/RECORD
