Metadata-Version: 2.1
Name: GrandExchangeToolbox
Version: 0.1.5
Summary: A package to interact with the Grand Exchange
Home-page: https://github.com/Lee-Tyrer/GrandExchange-ToolBox
Author: Lee
Author-email: lee.4lifee@gmail.com
License: UNKNOWN
Platform: UNKNOWN
Requires-Dist: requests
Requires-Dist: numpy
Requires-Dist: fuzzywuzzy
Requires-Dist: matplotlib
Requires-Dist: pyyaml
Requires-Dist: pydantic
